third_party.txt
third_party_licenses.txt
marimo/__init__.py
marimo/__main__.py
marimo/_loggers.py
marimo/_tracer.py
marimo/py.typed
marimo/_ai/__init__.py
marimo/_ai/_convert.py
marimo/_ai/_types.py
marimo/_ai/text_to_notebook.py
marimo/_ai/llm/__init__.py
marimo/_ai/llm/_impl.py
marimo/_ast/__init__.py
marimo/_ast/app.py
marimo/_ast/app_config.py
marimo/_ast/cell.py
marimo/_ast/cell_manager.py
marimo/_ast/codegen.py
marimo/_ast/compiler.py
marimo/_ast/errors.py
marimo/_ast/load.py
marimo/_ast/models.py
marimo/_ast/names.py
marimo/_ast/parse.py
marimo/_ast/pytest.py
marimo/_ast/sql_visitor.py
marimo/_ast/toplevel.py
marimo/_ast/transformers.py
marimo/_ast/variables.py
marimo/_ast/visitor.py
marimo/_cli/__init__.py
marimo/_cli/cli.py
marimo/_cli/cli_validators.py
marimo/_cli/envinfo.py
marimo/_cli/file_path.py
marimo/_cli/parse_args.py
marimo/_cli/print.py
marimo/_cli/run_docker.py
marimo/_cli/sandbox.py
marimo/_cli/upgrade.py
marimo/_cli/utils.py
marimo/_cli/config/commands.py
marimo/_cli/config/utils.py
marimo/_cli/convert/commands.py
marimo/_cli/convert/utils.py
marimo/_cli/development/commands.py
marimo/_cli/export/cloudflare.py
marimo/_cli/export/commands.py
marimo/_config/__init__.py
marimo/_config/cli_state.py
marimo/_config/config.py
marimo/_config/manager.py
marimo/_config/packages.py
marimo/_config/reader.py
marimo/_config/secrets.py
marimo/_config/settings.py
marimo/_config/utils.py
marimo/_convert/converters.py
marimo/_convert/ipynb.py
marimo/_convert/notebook.py
marimo/_convert/utils.py
marimo/_convert/markdown/markdown.py
marimo/_data/charts.py
marimo/_data/get_datasets.py
marimo/_data/models.py
marimo/_data/preview_column.py
marimo/_data/series.py
marimo/_data/sql_summaries.py
marimo/_dependencies/dependencies.py
marimo/_dependencies/errors.py
marimo/_entrypoints/ids.py
marimo/_entrypoints/registry.py
marimo/_islands/__init__.py
marimo/_islands/_island_generator.py
marimo/_lsp/index.cjs
marimo/_lsp/copilot/crypt32.node
aptiq-0.1.1.dist-info/METADATA
aptiq-0.1.1.dist-info/WHEEL
aptiq-0.1.1.dist-info/entry_points.txt
aptiq-0.1.1.dist-info/licenses/LICENSE
aptiq-0.1.1.dist-info/licenses/LICENSE.apache
aptiq-0.1.1.dist-info/licenses/LICENSE.proprietary
aptiq-0.1.1.dist-info/licenses/LICENSE.proprietary~
aptiq-0.1.1.dist-info/RECORD
