Metadata-Version: 2.4
Name: aptiq
Version: 0.1.1
Summary: A fork of marimo for collaborative work with a research agent
Project-URL: homepage, https://www.aptiqlabs.com/
License: DUAL LICENSE NOTICE
License-File: LICENSE
License-File: LICENSE.apache
License-File: LICENSE.proprietary
License-File: LICENSE.proprietary~
Classifier: Environment :: Console
Classifier: Environment :: Web Environment
Classifier: Intended Audience :: Developers
Classifier: Intended Audience :: Education
Classifier: Intended Audience :: Science/Research
Classifier: License :: OSI Approved :: Apache Software License
Classifier: Operating System :: OS Independent
Classifier: Programming Language :: Python
Classifier: Programming Language :: Python :: 3 :: Only
Classifier: Programming Language :: Python :: 3.9
Classifier: Programming Language :: Python :: 3.10
Classifier: Programming Language :: Python :: 3.11
Classifier: Programming Language :: Python :: 3.12
Classifier: Programming Language :: Python :: 3.13
Requires-Python: >=3.9
Requires-Dist: click<9,>=8.0
Requires-Dist: docutils>=0.16.0
Requires-Dist: itsdangerous>=2.0.0
Requires-Dist: jedi>=0.18.0
Requires-Dist: loro>=1.5.0; python_version >= '3.11'
Requires-Dist: markdown<4,>=3.4
Requires-Dist: narwhals>=1.12.0
Requires-Dist: packaging
Requires-Dist: psutil>=5.0
Requires-Dist: pygments<3,>=2.13
Requires-Dist: pymdown-extensions<11,>=10.11.2
Requires-Dist: pyyaml>=6.0
Requires-Dist: starlette!=0.36.0,>=0.26.1
Requires-Dist: tomlkit>=0.12.0
Requires-Dist: typing-extensions>=4.4.0; python_version < '3.11'
Requires-Dist: uvicorn>=0.22.0
Requires-Dist: websockets>=10.0.0
Provides-Extra: dev
Requires-Dist: black~=23.12.1; extra == 'dev'
Requires-Dist: click<9,>=8.0; extra == 'dev'
Requires-Dist: duckdb>=1.0.0; extra == 'dev'
Requires-Dist: openai>=1.55.3; extra == 'dev'
Requires-Dist: opentelemetry-api~=1.26.0; extra == 'dev'
Requires-Dist: opentelemetry-sdk~=1.26.0; extra == 'dev'
Requires-Dist: ruff~=0.9.1; extra == 'dev'
Requires-Dist: sqlglot>=23.4; extra == 'dev'
Provides-Extra: docs
Requires-Dist: cairosvg>=2.7.1; extra == 'docs'
Requires-Dist: mdx-include>=1.4.2; extra == 'docs'
Requires-Dist: mike>=2.0.0; extra == 'docs'
Requires-Dist: mkdocs-autorefs>=1.2.0; extra == 'docs'
Requires-Dist: mkdocs-click>=0.8.1; extra == 'docs'
Requires-Dist: mkdocs-git-revision-date-localized-plugin>=1.3.0; extra == 'docs'
Requires-Dist: mkdocs-glightbox>=0.4.0; extra == 'docs'
Requires-Dist: mkdocs-macros-plugin>=1.3.7; extra == 'docs'
Requires-Dist: mkdocs-material-extensions>=1.3.1; extra == 'docs'
Requires-Dist: mkdocs-material>=9.5.49; extra == 'docs'
Requires-Dist: mkdocs-minify-plugin>=0.8.0; extra == 'docs'
Requires-Dist: mkdocs-redirects>=1.2.2; extra == 'docs'
Requires-Dist: mkdocs>=1.6.1; extra == 'docs'
Requires-Dist: mkdocstrings[python]>=0.27.0; extra == 'docs'
Requires-Dist: pillow!=11.3.0,>=10.2.0; extra == 'docs'
Requires-Dist: pymdown-extensions>=10.7; extra == 'docs'
Provides-Extra: lsp
Requires-Dist: python-lsp-ruff>=2.0.0; extra == 'lsp'
Requires-Dist: python-lsp-server>=1.13.0; extra == 'lsp'
Provides-Extra: recommended
Requires-Dist: altair>=5.4.0; extra == 'recommended'
Requires-Dist: duckdb>=1.0.0; extra == 'recommended'
Requires-Dist: nbformat>=5.7.0; extra == 'recommended'
Requires-Dist: openai>=1.55.3; extra == 'recommended'
Requires-Dist: polars[pyarrow]>=1.9.0; extra == 'recommended'
Requires-Dist: ruff; extra == 'recommended'
Requires-Dist: sqlglot>=23.4; extra == 'recommended'
Provides-Extra: sql
Requires-Dist: duckdb>=1.0.0; extra == 'sql'
Requires-Dist: polars[pyarrow]>=1.9.0; extra == 'sql'
Requires-Dist: sqlglot>=23.4; extra == 'sql'
